Metadata-Version: 2.1
Name: tkscrollableframe
Version: 2.2
Summary: Scrollable frame widget for Tkinter
Home-page: https://github.com/edf1101/tkinter-Scrollable-Frame
Author: edf1101
Author-email: blank@blank.com
Classifier: Programming Language :: Python :: 3
Classifier: License :: OSI Approved :: MIT License
Classifier: Operating System :: OS Independent
License-File: LICENSE
